<?xml version="1.0" encoding="utf-8"?>
<katalog>
  <kategoriya>Аксессуары для ПК
     <podkategoriya>Клавиатура<produkcia>Microsoft</produkcia><cena>1 459 грн.</cena><marka> Microsoft WL Desktop 800 USB (2LF-00012)</marka><tip>Мультимедийная;</tip><interfeis>USB;</interfeis></podkategoriya><podkategoriya>Колонки<produkcia>TRUST</produkcia><cena>399 грн.</cena><marka> TRUST REMO 2.0 SPEAKER SET USB</marka><kanalov>2 канала</kanalov><interfeis>USB;</interfeis></podkategoriya></kategoriya>
  <kategoriya>Кулер
     <podkategoriya>для жесткого диска<produkcia>Deepcool Icedisk 2</produkcia><cena>115 грн.</cena><marka>Deepcool Icedisk 2 </marka><tip>	28 дБ</tip><interfeis>4 пиновый (Molex)</interfeis></podkategoriya><podkategoriya>для видеокарты<produkcia>Кулер DEEPCOOL Icedisk 1</produkcia><cena>76 грн.</cena><marka>DEEPCOOL Icedisk 1 </marka><tip>28 дБ</tip><interfeis>12 В;</interfeis></podkategoriya></kategoriya>
  <kategoriya>Беспроводное оборудование
     <podkategoriya>Wi-Fi роутер <produkcia>Wi-Fi роутер TP-LINK </produkcia><cena>399 грн.</cena><marka>TP-LINK TL-WR841N</marka><tip>Беспроводной маршрутизатор (роутер)</tip><interfeis>4x 10/100 Ethernet</interfeis></podkategoriya><podkategoriya>Адаптер Wi-Fi<produkcia>Адаптер Wi-FiTP-LINK </produkcia><cena>270 грн.</cena><marka>TP-LINK TL-WN722N</marka><tip>Беспроводной адаптер</tip><interfeis>USB 2.0</interfeis></podkategoriya></kategoriya>
  <kategoriya>Флеш память USB
     <podkategoriya>Флеш память USB<produkcia>Kingston DataTraveler SE9 32GB </produkcia><cena>228 грн.</cena><marka> (DTSE9H/32GB) </marka><tip>монобок</tip><interfeis>USB 2.0</interfeis></podkategoriya><podkategoriya>Флеш память USB<produkcia>Transcend JetDrive Go 300 64GB Silver </produkcia><cena>2499 грн.</cena><marka>TS64GJDG300S</marka><tip>Моноблок</tip><interfeis>USB 3.1 / Lightning</interfeis></podkategoriya></kategoriya>
  <kategoriya>Жесткий диск<podkategoriya>Внутренние HDD <produkcia>Hitachi 7K1000</produkcia><cena>1339 грн.</cena><marka> SATA III 1000Gb 7200rpm 32mb  (0J22423)</marka><tip>	портативные ПК</tip><interfeis>SATA III</interfeis></podkategoriya><podkategoriya>Внешние HDD<produkcia>Внешние HDD StoreJet 25M3 </produkcia><cena>1669 грн.</cena><marka>StoreJet 25M3 </marka><tip>Внешние HDD</tip><interfeis>USB 3.0</interfeis></podkategoriya></kategoriya>
  <kategoriya>Модули памяти<podkategoriya>настольные ПК<produkcia>Samsung  </produkcia><cena>339 грн.</cena><marka> Samsung (SAMD7AUDR-50M48)</marka><tip>DDR</tip><interfeis>1 Gb</interfeis></podkategoriya><podkategoriya>портативные ПК<produkcia>GOODRAM (GR1333S364L9S/4G)</produkcia><cena>435 грн.</cena><marka>SO-DIMM DDR III 4 Gb 1333 Mhz PC-10600</marka><tip>SO-DIMM DDR III</tip><interfeis>4 Gb</interfeis></podkategoriya></kategoriya>
  <kategoriya>Термопаста<podkategoriya>системы охлождения<produkcia>системы охлождения Titan</produkcia><cena>77грн.</cena><marka>Titan TTG-G30030</marka><tip>Термопаста</tip></podkategoriya><podkategoriya>системы охлождения<produkcia>системы охлождения Titan</produkcia><cena>4 грн.7</cena><marka>Titan TTG-G30015</marka><tip>Термопаста</tip></podkategoriya></kategoriya>
  <kategoriya>Материнская плата<podkategoriya>Геймерские<produkcia>Asus Z170-P (s1151, Intel Z170, PCI-Ex16) </produkcia><cena>3520грн.</cena><marka>Asus Z170-P</marka><tip>	Intel Z170</tip><interfeis>	4 x DDR4 DIMM; Количество каналов 2</interfeis></podkategoriya><podkategoriya>Обычные<produkcia> Socket 1150 ASUS H81M-K </produkcia><cena>1280грн.</cena><marka>Socket 1150 ASUS H81M-K (90MB0HI0-M0EAY0)</marka><tip>DDR 3</tip><interfeis>16 Gb</interfeis></podkategoriya></kategoriya>
  <kategoriya>Сетевая карта<podkategoriya>Разрядность шины PCI/PCI-X:32-bit<produkcia>TP-LINK TF-3239DL </produkcia><cena>123грн.</cena><marka>TF-3239DL </marka><tip>10/100 Мбит/с, чип Realtek RTL8139D, 1х RJ-45</tip><interfeis>	PCI 2.2, 32-bit</interfeis></podkategoriya><podkategoriya>Разрядность шины PCI/PCI-X:64-bit <produkcia>D-link DGE-550SX</produkcia><cena>2509грн.</cena><marka>DGE-550SX</marka><tip>10/100/1000 Мбит/с, 2х RJ-45</tip><interfeis>64-bit, 66 МГц</interfeis></podkategoriya></kategoriya>
  <kategoriya>Видео карта<podkategoriya>Производитель GPU:AMD
<produkcia>MSI R9 390 GAMING 8G</produkcia><cena>7973грн.</cena><marka>Radeon R9 390</marka><tip>MSI</tip><interfeis>	PCI Express 3.0 x16</interfeis></podkategoriya><podkategoriya>Производитель GPU:NVIDIA<produkcia>MSI GTX 950 Gaming 2G</produkcia><cena>4250грн.</cena><marka>GDDR5</marka><tip>GDDR5</tip><interfeis>PCI Express 3.0 x16</interfeis></podkategoriya></kategoriya>
  <kategoriya>Блок питания<podkategoriya>Модульное подключение кабелей:есть<produkcia>Chieftec A-80 CTG-650C</produkcia><cena>1597грн.</cena><marka>CTG-650C</marka><tip>4pin, 8pin</tip><SATA>	6</SATA></podkategoriya><podkategoriya>Модульное подключение кабелей:нет<produkcia>Aerocool KCAS-600</produkcia><cena>1325грн.</cena><marka>KCAS-600</marka><tip>20+4 pin</tip><SATA>7</SATA></podkategoriya></kategoriya>
  <kategoriya>Коммутаторы<podkategoriya>коммутатор неуправляемый<produkcia>TP-LINK</produkcia><cena>213грн.</cena><marka>TL-SF1008D</marka><tip>Коммутатор неуправляемый</tip><pitanie>адаптер</pitanie></podkategoriya><podkategoriya>коммутатор управляемый уровня 2<produkcia>Mikrotik RB260GS</produkcia><cena>952грн.</cena><marka>RB260GS</marka><tip>Коммутатор управляемый уровня 2</tip><pitanie>адаптер/PoE</pitanie></podkategoriya></kategoriya>
  <kategoriya>ТВ тюнер<podkategoriya>ТВ-тюнер внешний MyGica T230<produkcia>MyGica</produkcia><cena>575грн.</cena><marka>T230</marka><tip>ТВ-тюнер внешний</tip><interfeis>USB</interfeis></podkategoriya></kategoriya>
  <kategoriya>Оптические приборы<podkategoriya>Динамический конструктор Оптические приборы <produkcia>fischertechnik </produkcia><cena>2750грн.</cena><marka>FT-520399</marka><tip>Динамический конструктор</tip></podkategoriya></kategoriya>
</katalog>